setup.py
coded4/__init__.py
coded4/__main__.py
coded4/approx.py
coded4/cluster.py
coded4/output.py
coded4/stats.py
coded4/utils.py
coded4/vcs.py
coded4.egg-info/PKG-INFO
coded4.egg-info/SOURCES.txt
coded4.egg-info/dependency_links.txt
coded4.egg-info/entry_points.txt
coded4.egg-info/top_level.txt