Metadata-Version: 1.0
Name: coded4
Version: 0.3.3
Summary: Time-based statistics for Git and Hg repositories
Home-page: http://github.com/Xion/coded4
Author: Karol Kuczmarski "Xion"
Author-email: karol.kuczmarski@gmail.com
License: MIT
Platform: UNKNOWN
Classifier: Development Status :: 4 - Beta
Classifier: Intended Audience :: Developers
Classifier: Intended Audience :: Information Technology
Classifier: License :: OSI Approved :: MIT License
Classifier: Operating System :: OS Independent
Classifier: Programming Language :: Python
Classifier: Programming Language :: Python :: 2.6
Classifier: Programming Language :: Python :: 2.7
Classifier: Topic :: Software Development
